gremlite/__init__.py
gremlite/base.py
gremlite/connection.py
gremlite/cursors.py
gremlite/errors.py
gremlite/filtering.py
gremlite/querytools.py
gremlite/results.py
gremlite/steps.py
gremlite-0.1.2.dist-info/LICENSE
gremlite-0.1.2.dist-info/METADATA
gremlite-0.1.2.dist-info/WHEEL
gremlite-0.1.2.dist-info/top_level.txt
gremlite-0.1.2.dist-info/RECORD
