Metadata-Version: 2.1
Name: gremlite
Version: 0.1.2
Summary: Serverless graph database using Gremlin with SQLite
Home-page: https://github.com/skieffer/gremlite
License: Apache 2.0
Classifier: License :: OSI Approved :: Apache Software License
Classifier: Programming Language :: Python :: 3
Requires-Python: >=3.8
License-File: LICENSE
Requires-Dist: gremlinpython >=3.7.0
Provides-Extra: dev
Requires-Dist: pytest ; extra == 'dev'
Requires-Dist: pytest-cov ; extra == 'dev'
Requires-Dist: build ; extra == 'dev'
Requires-Dist: twine ; extra == 'dev'
Requires-Dist: invoke ; extra == 'dev'
